{
  "processor": "SetPermissionsProcessor",
  "query": "TYPE:'cm:folder' AND PATH:\"/app:company_home/st:sites/cm:gddm//*\" AND cm:name:'WIP'",
  "properties": {
    "cm:publisher": "saidone",
    "cm:contributor": "saidone"
  },
  "permissions": {
    "isInheritanceEnabled": false,
    "locallySet": [
      {
        "authorityId": "GROUP_gddm_administrators",
        "name": "SiteManager",
        "accessStatus": "ALLOWED"
      }
    ]
  },
  "aspects": [
    "cm:dublincore"
  ],
  "readOnly": true
}